env_attributes/__init__.py
env_attributes/environment.py
env_attributes-1.0.0.dist-info/METADATA
env_attributes-1.0.0.dist-info/WHEEL
env_attributes-1.0.0.dist-info/top_level.txt
env_attributes-1.0.0.dist-info/RECORD
