Metadata-Version: 2.1
Name: env-attributes
Version: 1.0.0
Summary: Loads environment into class attributes
Home-page: https://github.com/frezX/env_attributes
Author: frezX
Author-email: fffrrreeezzz.xxx@gmail.com
License: UNKNOWN
Keywords: python,dotenv,python-dotenv,python_dotenv,env_attributes,attributes,env,environment
Platform: UNKNOWN
Classifier: Intended Audience :: Developers
Classifier: Programming Language :: Python
Classifier: Programming Language :: Python :: 3
Classifier: Programming Language :: Python :: 3.7
Classifier: Programming Language :: Python :: Implementation :: CPython
Classifier: Programming Language :: Python :: Implementation :: PyPy
Requires-Python: >=3.7.0
Requires-Dist: python-dotenv
